sharebear/__init__.py
sharebear/cli.py
sharebear/sharebear.py
sharebear/sharebearjson.py
sharebear-0.4.1.dist-info/AUTHORS.rst
sharebear-0.4.1.dist-info/LICENSE
sharebear-0.4.1.dist-info/METADATA
sharebear-0.4.1.dist-info/WHEEL
sharebear-0.4.1.dist-info/entry_points.txt
sharebear-0.4.1.dist-info/top_level.txt
sharebear-0.4.1.dist-info/RECORD
