Metadata-Version: 2.1
Name: sharebear
Version: 0.4.1
Summary: This project provides a simple api for setting and getting variables and objects from a text file.
Home-page: https://github.com/bendhouseart/sharebear
Author: Anthony Edward Galassi
Author-email: anthony.galassi@protonmail.com
License: BSD license
Keywords: sharebear
Platform: UNKNOWN
Classifier: Development Status :: 2 - Pre-Alpha
Classifier: Intended Audience :: Developers
Classifier: License :: OSI Approved :: BSD License
Classifier: Natural Language :: English
Classifier: Programming Language :: Python :: 3
Classifier: Programming Language :: Python :: 3.5
Classifier: Programming Language :: Python :: 3.6
Classifier: Programming Language :: Python :: 3.7
Classifier: Programming Language :: Python :: 3.8
Requires-Python: >=3.5
Requires-Dist: pyyaml
